[{"title":"AddMoney","message":"**✪  Wildz (citizenid: 4 | id: 1)** $1000 (cash) added, new cash balance: 411000 reason: Admin Action","time":1717560390,"from":"playermoney"},{"title":"RemoveMoney","message":"**✪  Wildz (citizenid: 4 | id: 1)** $1000 (cash) removed, new cash balance: 410000 reason: Admin Action","time":1717560396,"from":"playermoney"},{"title":"AddMoney","message":"**✪  Wildz (citizenid: 4 | id: 1)** $1000 (bank) added, new bank balance: 41250 reason: Admin Action","time":1717560401,"from":"playermoney"},{"title":"RemoveMoney","message":"**✪  Wildz (citizenid: 4 | id: 1)** $1000 (bank) removed, new bank balance: 40250 reason: Admin Action","time":1717560405,"from":"playermoney"},{"title":"Dropped","message":"**✪  Wildz** (license:5e26656bb3a0fbe4a536ea11b6e6a617c36e45bf) left..\n **Reason:** Exiting","time":1717561909,"from":"joinleave"},{"title":"Dropped","message":"**✪  Wildz** (license:5e26656bb3a0fbe4a536ea11b6e6a617c36e45bf) left..\n **Reason:** Exiting","time":1717563661,"from":"joinleave"}]